cefkivy/__init__.py
cefkivy/browser.py
cefkivy/cefkeyboard.py
cefkivy/example.py
cefkivy/keycodes.py
cefkivy/popup.kv
cefkivy/popup.py
cefkivy/components/__init__.py
cefkivy/components/blockdialog.py
cefkivy/components/dialog.py
cefkivy/components/jsdialog.py
cefkivy/handlers/__init__.py
cefkivy/handlers/base.py
cefkivy/handlers/display.py
cefkivy/handlers/download.py
cefkivy/handlers/jsdialog.py
cefkivy/handlers/keyboard.py
cefkivy/handlers/lifespan.py
cefkivy/handlers/load.py
cefkivy/handlers/render.py
cefkivy/handlers/request.py
cefkivy_ebs-66.0.3.dist-info/LICENSE
cefkivy_ebs-66.0.3.dist-info/METADATA
cefkivy_ebs-66.0.3.dist-info/WHEEL
cefkivy_ebs-66.0.3.dist-info/entry_points.txt
cefkivy_ebs-66.0.3.dist-info/top_level.txt
cefkivy_ebs-66.0.3.dist-info/RECORD
