Metadata-Version: 2.1
Name: cefkivy-ebs
Version: 66.0.3
Summary: UNKNOWN
Home-page: https://github.com/ebs-universe/cefkivy
Author: Rentouch GmbH
Author-email: info@rentouch.ch
Maintainer: Chintalagiri Shashank
Maintainer-email: shashank@chintal.in
License: UNKNOWN
Platform: UNKNOWN
Requires-Python: >=3.4, <3.8
Requires-Dist: kivy-garden.frostedglass
Requires-Dist: cefpython3 (==66.0)
Requires-Dist: kivy
